{
  "type": "FeatureCollection",
  "features": [
    {
      "type": "Feature",
      "properties": {
        "marker-color": "#ff0000",
        "marker-size": "medium",
        "marker-symbol": "circle",
        "Name": "Massachussetts Institute of Technology",
        "Rank": 1,
        "AcceptanceRate": "24%"
      },
      "geometry": {
        "type": "Point",
        "coordinates": [
          -71.092,
          42.36
        ]
      }
    },
    {
      "type": "Feature",
      "properties": {
        "marker-color": "#ff0000",
        "marker-size": "medium",
        "marker-symbol": "circle",
        "Name": "University of California,Berkely",
        "Rank": 2,
        "AcceptanceRate": "18%"
      },
      "geometry": {
        "type": "Point",
        "coordinates": [
          -122.25,
          37.87
        ]
      }
    },
    {
      "type": "Feature",
      "properties": {
        "marker-color": "#008000",
        "marker-size": "medium",
        "marker-symbol": "circle",
        "Name": "University of North Carolina at Chapel Hill",
        "Rank": 3,
        "AcceptanceRate": "29%"
      },
      "geometry": {
        "type": "Point",
        "coordinates": [
          -79.04,
          35.9
        ]
      }
    },
    {
      "type": "Feature",
      "properties": {
        "marker-color": "#ffff00",
        "marker-size": "medium",
        "marker-symbol": "circle",
        "Name": "University of California,Los Angeles",
        "Rank": 4,
        "AcceptanceRate": "47%"
      },
      "geometry": {
        "type": "Point",
        "coordinates": [
          -118.44,
          34.06
        ]
      }
    },
    {
      "type": "Feature",
      "properties": {
        "marker-color": "#008000",
        "marker-size": "medium",
        "marker-symbol": "circle",
        "Name": "Rutgers, The State University of New Jersey",
        "Rank": 5,
        "AcceptanceRate": "65%"
      },
      "geometry": {
        "type": "Point",
        "coordinates": [
          -74.44,
          40.49
        ]
      }
    },
    {
      "type": "Feature",
      "properties": {
        "marker-color": "#ff0000",
        "marker-size": "medium",
        "marker-symbol": "circle",
        "Name": "Harvard University ",
        "Rank": 6,
        "AcceptanceRate": "22%"
      },
      "geometry": {
        "type": "Point",
        "coordinates": [
          -71.11,
          42.37
        ]
      }
    },
    {
      "type": "Feature",
      "properties": {
        "marker-color": "#008000",
        "marker-size": "medium",
        "marker-symbol": "circle",
        "Name": "Georgia Institute of Technology ",
        "Rank": 7,
        "AcceptanceRate": "76%"
      },
      "geometry": {
        "type": "Point",
        "coordinates": [
          -84.39,
          33.77
        ]
      }
    },
    {
      "type": "Feature",
      "properties": {
        "marker-color": "#ffff00",
        "marker-size": "medium",
        "marker-symbol": "circle",
        "Name": "University of Illinois Urbana-Champaign",
        "Rank": 8,
        "AcceptanceRate": "53%"
      },
      "geometry": {
        "type": "Point",
        "coordinates": [
          -88.22,
          40.1
        ]
      }
    },
    {
      "type": "Feature",
      "properties": {
        "marker-color": "#008000",
        "marker-size": "medium",
        "marker-symbol": "circle",
        "Name": "University of Southern California",
        "Rank": 9,
        "AcceptanceRate": "72%"
      },
      "geometry": {
        "type": "Point",
        "coordinates": [
          -118.28,
          34.02
        ]
      }
    },
    {
      "type": "Feature",
      "properties": {
        "marker-color": "#ffff00",
        "marker-size": "medium",
        "marker-symbol": "circle",
        "Name": "Cornell University",
        "Rank": 10,
        "AcceptanceRate": "56%"
      },
      "geometry": {
        "type": "Point",
        "coordinates": [
          -76.47,
          42.45
        ]
      }
    }
  ]
}